zesl.py
zesl-0.1.0.dist-info/WHEEL
zesl-0.1.0.dist-info/METADATA
zesl-0.1.0.dist-info/RECORD
