Metadata-Version: 2.1
Name: zesl
Version: 0.1.0
Summary: Zayne's Extremely Simple Language
Author: Zayne Marsh
Requires-Python: >=3.4,<4.0
Classifier: Programming Language :: Python :: 3
Classifier: Programming Language :: Python :: 3.4
Classifier: Programming Language :: Python :: 3.5
Classifier: Programming Language :: Python :: 3.6
Classifier: Programming Language :: Python :: 3.7
Classifier: Programming Language :: Python :: 3.8
Classifier: Programming Language :: Python :: 3.9
Classifier: Programming Language :: Python :: 3.10
Classifier: Programming Language :: Python :: 3.11
Requires-Dist: lark (>=1.1.5,<2.0.0)
